calc/__init__.py
calc/operations.py
jkhbfea-0.2.0.dist-info/METADATA
jkhbfea-0.2.0.dist-info/WHEEL
jkhbfea-0.2.0.dist-info/top_level.txt
jkhbfea-0.2.0.dist-info/RECORD
