Metadata-Version: 2.4
Name: jkhbfea
Version: 0.2.0
Summary: Une simple bibliothèque pour faire des calculs et d'autres fonctions utilitaires.
Author: jkhbfea
License: MIT
Classifier: Programming Language :: Python :: 3
Classifier: Operating System :: OS Independent
Requires-Python: >=3.7
Requires-Dist: cryptography
